{"commitInfo":{"timestamp":1774174391759,"operation":"MERGE","operationParameters":{"predicate":"[\"(((team_name#139 = team_name#5) AND (match_date#140 = match_date#22)) AND (opponent#141 = opponent#23))\"]","matchedPredicates":"[{\"actionType\":\"update\"}]","notMatchedPredicates":"[{\"actionType\":\"insert\"}]","notMatchedBySourcePredicates":"[]"},"readVersion":4,"isolationLevel":"Serializable","isBlindAppend":false,"operationMetrics":{"numTargetRowsCopied":"0","numTargetRowsDeleted":"0","numTargetFilesAdded":"1","numTargetBytesAdded":"9748","numTargetBytesRemoved":"9748","numTargetDeletionVectorsAdded":"0","numTargetRowsMatchedUpdated":"602","executionTimeMs":"27075","numTargetRowsInserted":"0","numTargetRowsMatchedDeleted":"0","numTargetDeletionVectorsUpdated":"0","scanTimeMs":"22074","numTargetRowsUpdated":"602","numOutputRows":"602","numTargetDeletionVectorsRemoved":"0","numTargetRowsNotMatchedBySourceUpdated":"0","numTargetChangeFilesAdded":"0","numSourceRows":"602","numTargetFilesRemoved":"1","numTargetRowsNotMatchedBySourceDeleted":"0","rewriteTimeMs":"3710"},"engineInfo":"Apache-Spark/3.5.1 Delta-Lake/3.1.0","txnId":"fe2d7417-3419-42b0-b7ec-5c3190ad3b80"}}
{"add":{"path":"part-00000-ebc741d2-1f75-42aa-8a62-47b1869ed127-c000.snappy.parquet","partitionValues":{},"size":9748,"modificationTime":1774174391359,"dataChange":true,"stats":"{\"numRecords\":602,\"minValues\":{\"team_name\":\"Arsenal\",\"match_date\":\"Aug 15, 2025\",\"opponent\":\"Arsenal\",\"home_away\":\"a\",\"result_status\":\"d\",\"goals_scored\":0,\"goals_conceded\":0,\"xg_for\":0.03,\"xg_against\":0.03,\"updated_at\":\"2025-08-01T00:00:00.000+02:00\",\"load_date\":\"2026-03-21\"},\"maxValues\":{\"team_name\":\"Wolverhampton Wanderers\",\"match_date\":\"Sep 29, 2025\",\"opponent\":\"Wolverhampton Wanderers\",\"home_away\":\"h\",\"result_status\":\"w\",\"goals_scored\":5,\"goals_conceded\":5,\"xg_for\":4.56,\"xg_against\":4.56,\"updated_at\":\"2025-08-01T00:00:00.000+02:00\",\"load_date\":\"2026-03-21\"},\"nullCount\":{\"team_name\":0,\"match_date\":0,\"opponent\":0,\"home_away\":0,\"result_status\":0,\"goals_scored\":0,\"goals_conceded\":0,\"xg_for\":0,\"xg_against\":0,\"updated_at\":0,\"load_date\":0}}"}}
{"remove":{"path":"part-00000-6d27f7d1-5b7c-4f44-b62e-36d60aa1d2bb-c000.snappy.parquet","deletionTimestamp":1774174391577,"dataChange":true,"extendedFileMetadata":true,"partitionValues":{},"size":9748,"stats":"{\"numRecords\":602}"}}
